community_uploader/__init__.py
community_uploader/exceptions.py
community_uploader/py.typed
community_uploader/types.py
community_uploader/uploader.py
community_uploader-1.0.1.dist-info/METADATA
community_uploader-1.0.1.dist-info/WHEEL
community_uploader-1.0.1.dist-info/top_level.txt
community_uploader-1.0.1.dist-info/RECORD
