Metadata-Version: 2.4
Name: community-uploader
Version: 1.0.1
Summary: 社区文件上传 SDK - 支持分片上传、断点续传、文件去重
Author-email: Tamar Team <dev@tamar.com>
License: MIT
Project-URL: Homepage, https://github.com/tamar/community-uploader-python
Keywords: upload,oss,multipart,async
Classifier: Development Status :: 4 - Beta
Classifier: Intended Audience :: Developers
Classifier: License :: OSI Approved :: MIT License
Classifier: Programming Language :: Python :: 3
Classifier: Programming Language :: Python :: 3.9
Classifier: Programming Language :: Python :: 3.10
Classifier: Programming Language :: Python :: 3.11
Classifier: Programming Language :: Python :: 3.12
Classifier: Framework :: AsyncIO
Requires-Python: >=3.9
Requires-Dist: aiohttp>=3.8.0
Requires-Dist: aiofiles>=23.0.0
Provides-Extra: dev
Requires-Dist: pytest>=7.0.0; extra == "dev"
Requires-Dist: pytest-asyncio>=0.21.0; extra == "dev"
